HomeDirectory-0.1.2.data/scripts/run.sh
HomeDirectory-0.1.2.data/scripts/setup.sh
src/__init__.py
src/homedirectory.py
HomeDirectory-0.1.2.dist-info/LICENCE
HomeDirectory-0.1.2.dist-info/METADATA
HomeDirectory-0.1.2.dist-info/WHEEL
HomeDirectory-0.1.2.dist-info/top_level.txt
HomeDirectory-0.1.2.dist-info/RECORD
