Metadata-Version: 2.1
Name: HomeDirectory
Version: 0.1.2
Summary: Sets up a basic function to print and show the Home Directory of the current Terminal.
Author: kunaalg
Author-email: <kunaal@runcode.in>
Keywords: python,homedirectory,home,directory,root,hd
Classifier: Development Status :: 4 - Beta
Classifier: Intended Audience :: Developers
Classifier: Programming Language :: Python :: 3
Classifier: Operating System :: Unix
Classifier: Operating System :: MacOS :: MacOS X
Classifier: Operating System :: Microsoft :: Windows
License-File: LICENCE
Requires-Dist: datetime
Requires-Dist: requests
Requires-Dist: virtualenv
